solid_angle_utils/__init__.py
solid_angle_utils/version.py
solid_angle_utils/cone/__init__.py
solid_angle_utils/cone/cone.py
solid_angle_utils/cone/mazonka2012solid.py
solid_angle_utils/triangle/__init__.py
solid_angle_utils-0.1.2.dist-info/LICENSE
solid_angle_utils-0.1.2.dist-info/METADATA
solid_angle_utils-0.1.2.dist-info/WHEEL
solid_angle_utils-0.1.2.dist-info/top_level.txt
solid_angle_utils-0.1.2.dist-info/RECORD
