Metadata-Version: 2.1
Name: solid_angle_utils
Version: 0.1.2
Summary: Helps you with solid angles and cones.
Home-page: https://github.com/cherenkov-plenoscope/solid_angle_utils
Author: Sebastian Achim Mueller
Author-email: sebastian-achim.mueller@mpi-hd.mpg.de
Classifier: Programming Language :: Python :: 3
Classifier: License :: OSI Approved :: MIT License
Classifier: Operating System :: OS Independent
Classifier: Natural Language :: English
Classifier: Intended Audience :: Science/Research
License-File: LICENSE
